examples/buffered_dummy_example.py
examples/buffered_dummy_example_compensation.py
examples/device_object_example.py
qumada/__init__.py
qumada/_version.py
qumada/metadata.py
qumada/instrument/__init__.py
qumada/instrument/buffered_instruments.py
qumada/instrument/instrument.py
qumada/instrument/buffers/__init__.py
qumada/instrument/buffers/buffer.py
qumada/instrument/buffers/dummy_dmm_buffer.py
qumada/instrument/buffers/mfli_buffer.py
qumada/instrument/buffers/sr830_buffer.py
qumada/instrument/custom_drivers/__init__.py
qumada/instrument/custom_drivers/Dummies/__init__.py
qumada/instrument/custom_drivers/Dummies/dummy_dac.py
qumada/instrument/custom_drivers/Dummies/dummy_dmm.py
qumada/instrument/custom_drivers/Harvard/Decadac.py
qumada/instrument/custom_drivers/Harvard/__init__.py
qumada/instrument/custom_drivers/QDevil/QDAC2.py
qumada/instrument/custom_drivers/ZI/MFLI.py
qumada/instrument/custom_drivers/ZI/__init__.py
qumada/instrument/mapping/__init__.py
qumada/instrument/mapping/base.py
qumada/instrument/mapping/mapping_gui.py
qumada/instrument/mapping/Dummies/DummyDac.py
qumada/instrument/mapping/Harvard/Decadac.py
qumada/instrument/mapping/QDevil/qdac.py
qumada/instrument/mapping/QDevil/qdac2.py
qumada/instrument/parameter_whitelists/param_whitelist.json
qumada/instrument/sims/__init__.py
qumada/measurement/__init__.py
qumada/measurement/device_object.py
qumada/measurement/jobs.py
qumada/measurement/measurement.py
qumada/measurement/doNd_enhanced/doNd_enhanced.py
qumada/measurement/scripts/__init__.py
qumada/measurement/scripts/generic_measurement.py
qumada/measurement/scripts/spectrometer.py
qumada/utils/GUI.py
qumada/utils/__init__.py
qumada/utils/browsefiles.py
qumada/utils/device_GUI.py
qumada/utils/generate_sweeps.py
qumada/utils/import_submodules.py
qumada/utils/init_station.py
qumada/utils/load_from_sqlite_db.py
qumada/utils/load_save_config.py
qumada/utils/parameter_file_helpers.py
qumada/utils/plotting.py
qumada/utils/ramp_parameter.py
qumada-2.0.2.dist-info/licenses/LICENSE
qumada-2.0.2.dist-info/METADATA
qumada-2.0.2.dist-info/WHEEL
qumada-2.0.2.dist-info/top_level.txt
qumada-2.0.2.dist-info/RECORD
