Metadata-Version: 2.4
Name: QuMADA
Version: 2.0.2
Summary: Measurement Abstraction and Database Access layer for QCoDeS
Author: JARA Institute for Quantum Information
License-Expression: LGPL-3.0-or-later
Project-URL: Repository, https://github.com/qutech/qumada
Project-URL: Documentation, https://qumada.readthedocs.io/en/latest/
Keywords: quantum,physics,abstraction,metadata,data management
Classifier: Programming Language :: Python :: 3
Classifier: Operating System :: OS Independent
Classifier: Topic :: Scientific/Engineering
Classifier: Intended Audience :: Science/Research
Requires-Python: >=3.9
License-File: LICENSE
Requires-Dist: qcodes>=0.46.0
Requires-Dist: qcodes_contrib_drivers>=0.18.0
Requires-Dist: matplotlib
Requires-Dist: jsonschema
Requires-Dist: zhinst-toolkit>=0.3.3
Requires-Dist: pyqt5
Requires-Dist: versioningit~=2.2.0
Provides-Extra: gui
Requires-Dist: plottr; extra == "gui"
Provides-Extra: spyder
Requires-Dist: spyder; extra == "spyder"
Dynamic: license-file
